setup.cfg
setup.py
pivottable/__init__.py
pivottable/pivottable.py
pivottable.egg-info/PKG-INFO
pivottable.egg-info/SOURCES.txt
pivottable.egg-info/dependency_links.txt
pivottable.egg-info/top_level.txt