Metadata-Version: 1.0
Name: pivottable
Version: 0.8
Summary: A module that will help you to generate Pivot Tables base on arbitrary objects
Home-page: https://bitbucket.org/marplatense/python-pivottable
Author: Mariano Mara
Author-email: mariano.mara@gmail.com
License: MIT License
Download-URL: https://bitbucket.org/marplatense/python-pivottable/downloads
Keywords: pivot,table,pivottable,python
Platform: UNKNOWN
Classifier: Development Status :: 4 - Beta
Classifier: Intended Audience :: Developers
Classifier: License :: OSI Approved :: MIT License
Classifier: Operating System :: OS Independent
Classifier: Programming Language :: Python
Classifier: Topic :: Software Development :: Libraries :: Python Modules
